wormutils_r/R_output.py
wormutils_r/__init__.py
wormutils_r/convert.py
wormutils_r-0.1.0.dist-info/licenses/LICENSE.txt
wormutils_r-0.1.0.dist-info/METADATA
wormutils_r-0.1.0.dist-info/WHEEL
wormutils_r-0.1.0.dist-info/top_level.txt
wormutils_r-0.1.0.dist-info/RECORD
