Metadata-Version: 2.4
Name: wormutils_r
Version: 0.1.0
Summary: A package for common functions containing R/rpy2 used in other WORM codes
Author: Grayson Boyer
Author-email: gmboyer@asu.edu
Classifier: Programming Language :: Python :: 3
Classifier: License :: OSI Approved :: MIT License
Classifier: Operating System :: OS Independent
Requires-Python: >=3.10
License-File: LICENSE.txt
Requires-Dist: rpy2
Requires-Dist: dill
Requires-Dist: pandas
Requires-Dist: numpy
Dynamic: author
Dynamic: author-email
Dynamic: classifier
Dynamic: description
Dynamic: description-content-type
Dynamic: license-file
Dynamic: requires-dist
Dynamic: requires-python
Dynamic: summary
